{"is_source_file": false, "format": "", "description": "", "external_files": [], "external_methods": [], "published": [], "classes": [], "methods": [], "calls": [], "search-terms": [], "state": 2, "file_id": 14, "knowledge_revision": 32, "git_revision": "b3b4cc41351ab101253ccc608c02d534ded2f520", "hash": "06e733283fa43d1dd57738cfc409adbd", "format-version": 4, "code-base-name": "todo_frontend", "filename": "todo_frontend/src/logo.svg", "revision_history": [{"32": "b3b4cc41351ab101253ccc608c02d534ded2f520"}]}